MANIFEST.in
psycopg2.py
setup.py
psycopg2cffi_compat.egg-info/PKG-INFO
psycopg2cffi_compat.egg-info/SOURCES.txt
psycopg2cffi_compat.egg-info/dependency_links.txt
psycopg2cffi_compat.egg-info/requires.txt
psycopg2cffi_compat.egg-info/top_level.txt