Metadata-Version: 1.1
Name: psycopg2cffi-compat
Version: 1.0
Summary: A Simple library to enable psycopg2 compatability
Home-page: https://github.com/dstufft/psycopg2cffi-compat
Author: Donald Stufft
Author-email: donald@stufft.io
License: Apache License v2.0
Platform: UNKNOWN
Classifier: License :: OSI Approved :: Apache Software License
Classifier: Programming Language :: Python
Classifier: Programming Language :: Python :: 2
Classifier: Programming Language :: Python :: 2.7
Classifier: Programming Language :: Python :: 3
Classifier: Programming Language :: Python :: 3.2
Classifier: Programming Language :: Python :: 3.3
Classifier: Programming Language :: Python :: Implementation :: CPython
Classifier: Programming Language :: Python :: Implementation :: PyPy
